{
	"env_props": {
		"run_env": "DEV",
		"locale": "EN",
		"run_env_strategy": "DEFAULT_ON_UNAVAIL",
		"locale_strategy": "DEFAULT_ON_UNAVAIL",
		"properties": [{
			"db_url": [{
				"dev": [{
					".": "postgres://localhost:5432/rustwebdev"
				}],
				"prod(site01)": [{
					".": "postgres://localhost:5431/rustwebdev"
				}],
				"prod(site02)": [{
					".": "postgres://localhost:5430/rustwebdev"
				}],
                "run_env_strategy": "ERR_ON_UNAVAIL"
			}],
	
            "docdb_url": [{
				"dev": [{
					".": "mongodb://localhost:27017/"
				}]
			}],

            "label_username": [{
				".": [{
					".": "User Name",
					"jp": "利用者名",
					"ch": "用户名"
				}]
			}]

		}]

	}
}